[ {
  "shipName" : "UZJhbICFMUV`WkW",
  "tonnage" : 1167,
  "arrivalTime" : {
    "time" : 1381
  },
  "unloadTime" : {
    "time" : 59
  },
  "typeCargo" : "BULK"
}, {
  "shipName" : "dX_NWeHUSffCcOV",
  "tonnage" : 1188,
  "arrivalTime" : {
    "time" : 1614
  },
  "unloadTime" : {
    "time" : 60
  },
  "typeCargo" : "CONTAINER"
}, {
  "shipName" : "XZAYUJS`]gV\\ENW",
  "tonnage" : 951,
  "arrivalTime" : {
    "time" : 3334
  },
  "unloadTime" : {
    "time" : 48
  },
  "typeCargo" : "CONTAINER"
}, {
  "shipName" : "LCV`NPYKYMGLcXE",
  "tonnage" : 905,
  "arrivalTime" : {
    "time" : 3471
  },
  "unloadTime" : {
    "time" : 46
  },
  "typeCargo" : "LIQUID"
}, {
  "shipName" : "jX\\NlHQR_QmHPJA",
  "tonnage" : 1196,
  "arrivalTime" : {
    "time" : 3486
  },
  "unloadTime" : {
    "time" : 60
  },
  "typeCargo" : "BULK"
}, {
  "shipName" : "PClZUL`UPZ[EGVI",
  "tonnage" : 997,
  "arrivalTime" : {
    "time" : 3551
  },
  "unloadTime" : {
    "time" : 50
  },
  "typeCargo" : "CONTAINER"
}, {
  "shipName" : "aVpZeZpQYTVSgIX",
  "tonnage" : 1071,
  "arrivalTime" : {
    "time" : 3574
  },
  "unloadTime" : {
    "time" : 54
  },
  "typeCargo" : "LIQUID"
}, {
  "shipName" : "DCdXZcVkgS]ha`L",
  "tonnage" : 1128,
  "arrivalTime" : {
    "time" : 3796
  },
  "unloadTime" : {
    "time" : 57
  },
  "typeCargo" : "LIQUID"
}, {
  "shipName" : "^X[IWsiuWXZDgwf",
  "tonnage" : 1110,
  "arrivalTime" : {
    "time" : 4265
  },
  "unloadTime" : {
    "time" : 56
  },
  "typeCargo" : "CONTAINER"
}, {
  "shipName" : "HoPBifpJNHQP`Y^",
  "tonnage" : 1152,
  "arrivalTime" : {
    "time" : 4776
  },
  "unloadTime" : {
    "time" : 58
  },
  "typeCargo" : "BULK"
}, {
  "shipName" : "SNUJbVfRUPSWbLV",
  "tonnage" : 976,
  "arrivalTime" : {
    "time" : 5120
  },
  "unloadTime" : {
    "time" : 49
  },
  "typeCargo" : "CONTAINER"
}, {
  "shipName" : "VKwRJwhxLRNT_Sf",
  "tonnage" : 1072,
  "arrivalTime" : {
    "time" : 5384
  },
  "unloadTime" : {
    "time" : 54
  },
  "typeCargo" : "LIQUID"
}, {
  "shipName" : "WfYhZlPZoJZLjkh",
  "tonnage" : 964,
  "arrivalTime" : {
    "time" : 5405
  },
  "unloadTime" : {
    "time" : 49
  },
  "typeCargo" : "CONTAINER"
}, {
  "shipName" : "\\HB_`A`QaKJ]b^Q",
  "tonnage" : 1165,
  "arrivalTime" : {
    "time" : 5935
  },
  "unloadTime" : {
    "time" : 59
  },
  "typeCargo" : "BULK"
}, {
  "shipName" : "IAdZTEnlKNCT\\fV",
  "tonnage" : 941,
  "arrivalTime" : {
    "time" : 5955
  },
  "unloadTime" : {
    "time" : 48
  },
  "typeCargo" : "BULK"
}, {
  "shipName" : "eYkHDQKEM[^QHTV",
  "tonnage" : 944,
  "arrivalTime" : {
    "time" : 5993
  },
  "unloadTime" : {
    "time" : 48
  },
  "typeCargo" : "CONTAINER"
}, {
  "shipName" : "fB\\TERMZXXivQRJ",
  "tonnage" : 1155,
  "arrivalTime" : {
    "time" : 6311
  },
  "unloadTime" : {
    "time" : 58
  },
  "typeCargo" : "LIQUID"
}, {
  "shipName" : "BibUmjOUQ^JIYsV",
  "tonnage" : 969,
  "arrivalTime" : {
    "time" : 6461
  },
  "unloadTime" : {
    "time" : 49
  },
  "typeCargo" : "BULK"
}, {
  "shipName" : "gbLRY`MbccTJeDS",
  "tonnage" : 1126,
  "arrivalTime" : {
    "time" : 6526
  },
  "unloadTime" : {
    "time" : 57
  },
  "typeCargo" : "BULK"
}, {
  "shipName" : "C`KGGdYQOMAcNPJ",
  "tonnage" : 962,
  "arrivalTime" : {
    "time" : 6650
  },
  "unloadTime" : {
    "time" : 49
  },
  "typeCargo" : "CONTAINER"
}, {
  "shipName" : "YEAnLqjRATX\\T]f",
  "tonnage" : 1140,
  "arrivalTime" : {
    "time" : 7011
  },
  "unloadTime" : {
    "time" : 57
  },
  "typeCargo" : "LIQUID"
}, {
  "shipName" : "s\\jRpVTLjNF]TWE",
  "tonnage" : 902,
  "arrivalTime" : {
    "time" : 7681
  },
  "unloadTime" : {
    "time" : 46
  },
  "typeCargo" : "BULK"
}, {
  "shipName" : "cYUXA^YDVsc_LKS",
  "tonnage" : 1020,
  "arrivalTime" : {
    "time" : 7741
  },
  "unloadTime" : {
    "time" : 51
  },
  "typeCargo" : "CONTAINER"
}, {
  "shipName" : "VbLWpYcbYZNb[wq",
  "tonnage" : 1079,
  "arrivalTime" : {
    "time" : 8040
  },
  "unloadTime" : {
    "time" : 54
  },
  "typeCargo" : "CONTAINER"
}, {
  "shipName" : "IhE\\kp`c_jD]TTB",
  "tonnage" : 1092,
  "arrivalTime" : {
    "time" : 8050
  },
  "unloadTime" : {
    "time" : 55
  },
  "typeCargo" : "CONTAINER"
}, {
  "shipName" : "cxpNUB\\DNEdBSEZ",
  "tonnage" : 1125,
  "arrivalTime" : {
    "time" : 8561
  },
  "unloadTime" : {
    "time" : 57
  },
  "typeCargo" : "CONTAINER"
}, {
  "shipName" : "WFgjNLLAdOe[aYq",
  "tonnage" : 1059,
  "arrivalTime" : {
    "time" : 8870
  },
  "unloadTime" : {
    "time" : 53
  },
  "typeCargo" : "BULK"
}, {
  "shipName" : "oImXJWZQO`IHYXM",
  "tonnage" : 944,
  "arrivalTime" : {
    "time" : 9103
  },
  "unloadTime" : {
    "time" : 48
  },
  "typeCargo" : "LIQUID"
}, {
  "shipName" : "ZLYx^TZNwXuRPNV",
  "tonnage" : 978,
  "arrivalTime" : {
    "time" : 9227
  },
  "unloadTime" : {
    "time" : 49
  },
  "typeCargo" : "CONTAINER"
}, {
  "shipName" : "Dabg^RYVMAa]OXH",
  "tonnage" : 1040,
  "arrivalTime" : {
    "time" : 9349
  },
  "unloadTime" : {
    "time" : 52
  },
  "typeCargo" : "LIQUID"
}, {
  "shipName" : "IcVFglaM`ZPaEbF",
  "tonnage" : 1090,
  "arrivalTime" : {
    "time" : 9360
  },
  "unloadTime" : {
    "time" : 55
  },
  "typeCargo" : "BULK"
}, {
  "shipName" : "WkOvaFL^mDVX]Xp",
  "tonnage" : 947,
  "arrivalTime" : {
    "time" : 9404
  },
  "unloadTime" : {
    "time" : 48
  },
  "typeCargo" : "BULK"
}, {
  "shipName" : "YjEEZONgW_^IjUf",
  "tonnage" : 906,
  "arrivalTime" : {
    "time" : 9478
  },
  "unloadTime" : {
    "time" : 46
  },
  "typeCargo" : "BULK"
}, {
  "shipName" : "vsRhO_VDXr_`TFO",
  "tonnage" : 939,
  "arrivalTime" : {
    "time" : 9567
  },
  "unloadTime" : {
    "time" : 47
  },
  "typeCargo" : "CONTAINER"
}, {
  "shipName" : "ARVs]P_HbTONI[[",
  "tonnage" : 915,
  "arrivalTime" : {
    "time" : 9868
  },
  "unloadTime" : {
    "time" : 46
  },
  "typeCargo" : "BULK"
}, {
  "shipName" : "MRHCobRnkpLab]M",
  "tonnage" : 947,
  "arrivalTime" : {
    "time" : 10181
  },
  "unloadTime" : {
    "time" : 48
  },
  "typeCargo" : "LIQUID"
}, {
  "shipName" : "eb^YiX_MUZfm`qh",
  "tonnage" : 1127,
  "arrivalTime" : {
    "time" : 10200
  },
  "unloadTime" : {
    "time" : 57
  },
  "typeCargo" : "BULK"
}, {
  "shipName" : "MY^UXCWObVHggNT",
  "tonnage" : 1127,
  "arrivalTime" : {
    "time" : 10323
  },
  "unloadTime" : {
    "time" : 57
  },
  "typeCargo" : "LIQUID"
}, {
  "shipName" : "[FhgUNl`QLFNlEU",
  "tonnage" : 972,
  "arrivalTime" : {
    "time" : 10405
  },
  "unloadTime" : {
    "time" : 49
  },
  "typeCargo" : "BULK"
}, {
  "shipName" : "DN`^pFXHPaeG_bT",
  "tonnage" : 914,
  "arrivalTime" : {
    "time" : 10577
  },
  "unloadTime" : {
    "time" : 46
  },
  "typeCargo" : "CONTAINER"
}, {
  "shipName" : "LRS\\ZcnXCDEToJt",
  "tonnage" : 1136,
  "arrivalTime" : {
    "time" : 10609
  },
  "unloadTime" : {
    "time" : 57
  },
  "typeCargo" : "LIQUID"
}, {
  "shipName" : "XAoODQcHhjO`MPb",
  "tonnage" : 1091,
  "arrivalTime" : {
    "time" : 10615
  },
  "unloadTime" : {
    "time" : 55
  },
  "typeCargo" : "LIQUID"
}, {
  "shipName" : "WFZDLMKeGt`lkdA",
  "tonnage" : 978,
  "arrivalTime" : {
    "time" : 10637
  },
  "unloadTime" : {
    "time" : 49
  },
  "typeCargo" : "CONTAINER"
}, {
  "shipName" : "YcOYjBLSZloXLHh",
  "tonnage" : 1115,
  "arrivalTime" : {
    "time" : 10935
  },
  "unloadTime" : {
    "time" : 56
  },
  "typeCargo" : "LIQUID"
}, {
  "shipName" : "P\\JYOMecm`PsSKS",
  "tonnage" : 1175,
  "arrivalTime" : {
    "time" : 10950
  },
  "unloadTime" : {
    "time" : 59
  },
  "typeCargo" : "LIQUID"
}, {
  "shipName" : "QgZUGKU`QIHligV",
  "tonnage" : 1197,
  "arrivalTime" : {
    "time" : 10957
  },
  "unloadTime" : {
    "time" : 60
  },
  "typeCargo" : "CONTAINER"
}, {
  "shipName" : "MQ\\SYTJVoPGLgFM",
  "tonnage" : 913,
  "arrivalTime" : {
    "time" : 10960
  },
  "unloadTime" : {
    "time" : 46
  },
  "typeCargo" : "LIQUID"
}, {
  "shipName" : "XjQO_FuGQgV]QYE",
  "tonnage" : 1092,
  "arrivalTime" : {
    "time" : 11016
  },
  "unloadTime" : {
    "time" : 55
  },
  "typeCargo" : "LIQUID"
}, {
  "shipName" : "TYuXRZbhNbFjPH`",
  "tonnage" : 1014,
  "arrivalTime" : {
    "time" : 11060
  },
  "unloadTime" : {
    "time" : 51
  },
  "typeCargo" : "LIQUID"
}, {
  "shipName" : "WfYaMW^_SOJWXeI",
  "tonnage" : 1118,
  "arrivalTime" : {
    "time" : 11180
  },
  "unloadTime" : {
    "time" : 56
  },
  "typeCargo" : "LIQUID"
}, {
  "shipName" : "TDX]YQjIMVDWCFR",
  "tonnage" : 984,
  "arrivalTime" : {
    "time" : 11462
  },
  "unloadTime" : {
    "time" : 50
  },
  "typeCargo" : "LIQUID"
}, {
  "shipName" : "bFDYPkLdHhCVsUS",
  "tonnage" : 1139,
  "arrivalTime" : {
    "time" : 11532
  },
  "unloadTime" : {
    "time" : 57
  },
  "typeCargo" : "LIQUID"
}, {
  "shipName" : "BURdImZnSBZE`kp",
  "tonnage" : 1043,
  "arrivalTime" : {
    "time" : 11720
  },
  "unloadTime" : {
    "time" : 53
  },
  "typeCargo" : "BULK"
}, {
  "shipName" : "pLvaCjLLLA]OSbA",
  "tonnage" : 1023,
  "arrivalTime" : {
    "time" : 11826
  },
  "unloadTime" : {
    "time" : 52
  },
  "typeCargo" : "CONTAINER"
}, {
  "shipName" : "TfRgVVoMepqGZOQ",
  "tonnage" : 1077,
  "arrivalTime" : {
    "time" : 11841
  },
  "unloadTime" : {
    "time" : 54
  },
  "typeCargo" : "BULK"
}, {
  "shipName" : "PdTTCWbIM_\\BRXg",
  "tonnage" : 1137,
  "arrivalTime" : {
    "time" : 11846
  },
  "unloadTime" : {
    "time" : 57
  },
  "typeCargo" : "BULK"
}, {
  "shipName" : "Yn[UmUV[^nSNGaR",
  "tonnage" : 1002,
  "arrivalTime" : {
    "time" : 11926
  },
  "unloadTime" : {
    "time" : 51
  },
  "typeCargo" : "BULK"
}, {
  "shipName" : "c`U^v]eNFBZ[ZFj",
  "tonnage" : 1146,
  "arrivalTime" : {
    "time" : 12146
  },
  "unloadTime" : {
    "time" : 58
  },
  "typeCargo" : "CONTAINER"
}, {
  "shipName" : "W]COI\\USuXEBMXa",
  "tonnage" : 1121,
  "arrivalTime" : {
    "time" : 12191
  },
  "unloadTime" : {
    "time" : 57
  },
  "typeCargo" : "LIQUID"
}, {
  "shipName" : "jUOnnBRB_]I\\PE[",
  "tonnage" : 946,
  "arrivalTime" : {
    "time" : 12309
  },
  "unloadTime" : {
    "time" : 48
  },
  "typeCargo" : "LIQUID"
}, {
  "shipName" : "XHkUt\\tYEUU`SYW",
  "tonnage" : 1129,
  "arrivalTime" : {
    "time" : 12452
  },
  "unloadTime" : {
    "time" : 57
  },
  "typeCargo" : "BULK"
}, {
  "shipName" : "KcZeS[UkO^EegSX",
  "tonnage" : 1143,
  "arrivalTime" : {
    "time" : 12780
  },
  "unloadTime" : {
    "time" : 58
  },
  "typeCargo" : "LIQUID"
}, {
  "shipName" : "W[jkqqHPHNKOggC",
  "tonnage" : 1196,
  "arrivalTime" : {
    "time" : 12782
  },
  "unloadTime" : {
    "time" : 60
  },
  "typeCargo" : "BULK"
}, {
  "shipName" : "XNaRCUMaGP^WgVC",
  "tonnage" : 1189,
  "arrivalTime" : {
    "time" : 12803
  },
  "unloadTime" : {
    "time" : 60
  },
  "typeCargo" : "LIQUID"
}, {
  "shipName" : "R^FcTsfPl`Z\\WWI",
  "tonnage" : 1197,
  "arrivalTime" : {
    "time" : 12821
  },
  "unloadTime" : {
    "time" : 60
  },
  "typeCargo" : "CONTAINER"
}, {
  "shipName" : "TPLdQV[oTk]QdYX",
  "tonnage" : 909,
  "arrivalTime" : {
    "time" : 12823
  },
  "unloadTime" : {
    "time" : 46
  },
  "typeCargo" : "LIQUID"
}, {
  "shipName" : "Y[ZbdYDTZYG`CjS",
  "tonnage" : 1106,
  "arrivalTime" : {
    "time" : 12833
  },
  "unloadTime" : {
    "time" : 56
  },
  "typeCargo" : "BULK"
}, {
  "shipName" : "aUD]WsrjZbXHOSd",
  "tonnage" : 948,
  "arrivalTime" : {
    "time" : 12887
  },
  "unloadTime" : {
    "time" : 48
  },
  "typeCargo" : "LIQUID"
}, {
  "shipName" : "PlchSQ`kBt]^wNL",
  "tonnage" : 1076,
  "arrivalTime" : {
    "time" : 12896
  },
  "unloadTime" : {
    "time" : 54
  },
  "typeCargo" : "LIQUID"
}, {
  "shipName" : "JTFBQjXFRhVOOMg",
  "tonnage" : 1027,
  "arrivalTime" : {
    "time" : 13012
  },
  "unloadTime" : {
    "time" : 52
  },
  "typeCargo" : "BULK"
}, {
  "shipName" : "\\WEwmTpQXGOLMQM",
  "tonnage" : 1167,
  "arrivalTime" : {
    "time" : 13034
  },
  "unloadTime" : {
    "time" : 59
  },
  "typeCargo" : "BULK"
}, {
  "shipName" : "VmXHPCPORf_DV]R",
  "tonnage" : 1046,
  "arrivalTime" : {
    "time" : 13039
  },
  "unloadTime" : {
    "time" : 53
  },
  "typeCargo" : "CONTAINER"
}, {
  "shipName" : "OJGOARmXTT[cTJs",
  "tonnage" : 1101,
  "arrivalTime" : {
    "time" : 13086
  },
  "unloadTime" : {
    "time" : 56
  },
  "typeCargo" : "BULK"
}, {
  "shipName" : "amYiq]\\ktOONY`V",
  "tonnage" : 1000,
  "arrivalTime" : {
    "time" : 13591
  },
  "unloadTime" : {
    "time" : 50
  },
  "typeCargo" : "LIQUID"
}, {
  "shipName" : "A`_XvVjfEFWSO[B",
  "tonnage" : 973,
  "arrivalTime" : {
    "time" : 14089
  },
  "unloadTime" : {
    "time" : 49
  },
  "typeCargo" : "CONTAINER"
}, {
  "shipName" : "PXISXWD\\QEugcl`",
  "tonnage" : 1186,
  "arrivalTime" : {
    "time" : 14292
  },
  "unloadTime" : {
    "time" : 60
  },
  "typeCargo" : "CONTAINER"
}, {
  "shipName" : "ZbCfTmCSfIVUXRD",
  "tonnage" : 949,
  "arrivalTime" : {
    "time" : 14393
  },
  "unloadTime" : {
    "time" : 48
  },
  "typeCargo" : "LIQUID"
}, {
  "shipName" : "aQTI][aSNFDqa^N",
  "tonnage" : 1024,
  "arrivalTime" : {
    "time" : 14906
  },
  "unloadTime" : {
    "time" : 52
  },
  "typeCargo" : "CONTAINER"
}, {
  "shipName" : "ImQcFZVTqISCNUI",
  "tonnage" : 982,
  "arrivalTime" : {
    "time" : 14918
  },
  "unloadTime" : {
    "time" : 50
  },
  "typeCargo" : "LIQUID"
}, {
  "shipName" : "MCJaHZBbSgYpV\\b",
  "tonnage" : 1147,
  "arrivalTime" : {
    "time" : 14936
  },
  "unloadTime" : {
    "time" : 58
  },
  "typeCargo" : "BULK"
}, {
  "shipName" : "ZWgFK_O[VszIFmW",
  "tonnage" : 1072,
  "arrivalTime" : {
    "time" : 14944
  },
  "unloadTime" : {
    "time" : 54
  },
  "typeCargo" : "BULK"
}, {
  "shipName" : "GFGCUTQeZPTNAkY",
  "tonnage" : 1016,
  "arrivalTime" : {
    "time" : 15176
  },
  "unloadTime" : {
    "time" : 51
  },
  "typeCargo" : "CONTAINER"
}, {
  "shipName" : "IoOVOMPUUikPWck",
  "tonnage" : 972,
  "arrivalTime" : {
    "time" : 15298
  },
  "unloadTime" : {
    "time" : 49
  },
  "typeCargo" : "CONTAINER"
}, {
  "shipName" : "OMl_TBFXSPP^ZiV",
  "tonnage" : 1120,
  "arrivalTime" : {
    "time" : 15314
  },
  "unloadTime" : {
    "time" : 56
  },
  "typeCargo" : "LIQUID"
}, {
  "shipName" : "LX\\TtRFKFWMNvrh",
  "tonnage" : 940,
  "arrivalTime" : {
    "time" : 15583
  },
  "unloadTime" : {
    "time" : 47
  },
  "typeCargo" : "BULK"
}, {
  "shipName" : "PKDNTRNQRTARVap",
  "tonnage" : 949,
  "arrivalTime" : {
    "time" : 15687
  },
  "unloadTime" : {
    "time" : 48
  },
  "typeCargo" : "CONTAINER"
}, {
  "shipName" : "uKLlrBOY\\HiIX\\P",
  "tonnage" : 1145,
  "arrivalTime" : {
    "time" : 15706
  },
  "unloadTime" : {
    "time" : 58
  },
  "typeCargo" : "BULK"
}, {
  "shipName" : "CxXSOSQdNgNYZJ\\",
  "tonnage" : 1062,
  "arrivalTime" : {
    "time" : 15826
  },
  "unloadTime" : {
    "time" : 54
  },
  "typeCargo" : "CONTAINER"
}, {
  "shipName" : "XA[lAMSRkZZWkVW",
  "tonnage" : 939,
  "arrivalTime" : {
    "time" : 15954
  },
  "unloadTime" : {
    "time" : 47
  },
  "typeCargo" : "CONTAINER"
}, {
  "shipName" : "\\WIlcJh[OVRZfnC",
  "tonnage" : 1148,
  "arrivalTime" : {
    "time" : 16009
  },
  "unloadTime" : {
    "time" : 58
  },
  "typeCargo" : "LIQUID"
}, {
  "shipName" : "XgIWX_lQfMVK_KT",
  "tonnage" : 1152,
  "arrivalTime" : {
    "time" : 16090
  },
  "unloadTime" : {
    "time" : 58
  },
  "typeCargo" : "BULK"
}, {
  "shipName" : "P^facVNPMeLTNfO",
  "tonnage" : 1077,
  "arrivalTime" : {
    "time" : 16124
  },
  "unloadTime" : {
    "time" : 54
  },
  "typeCargo" : "CONTAINER"
}, {
  "shipName" : "CXWqYK^NTXUTUJW",
  "tonnage" : 1057,
  "arrivalTime" : {
    "time" : 16301
  },
  "unloadTime" : {
    "time" : 53
  },
  "typeCargo" : "BULK"
}, {
  "shipName" : "MH]QVTxO[wRmYxm",
  "tonnage" : 1168,
  "arrivalTime" : {
    "time" : 16308
  },
  "unloadTime" : {
    "time" : 59
  },
  "typeCargo" : "CONTAINER"
}, {
  "shipName" : "SqMOX\\HZPKGCAMV",
  "tonnage" : 1140,
  "arrivalTime" : {
    "time" : 16374
  },
  "unloadTime" : {
    "time" : 57
  },
  "typeCargo" : "LIQUID"
}, {
  "shipName" : "TLXGeReMdWZfIKf",
  "tonnage" : 1135,
  "arrivalTime" : {
    "time" : 16428
  },
  "unloadTime" : {
    "time" : 57
  },
  "typeCargo" : "LIQUID"
}, {
  "shipName" : "MOZVa`^]C_cKHoW",
  "tonnage" : 991,
  "arrivalTime" : {
    "time" : 16446
  },
  "unloadTime" : {
    "time" : 50
  },
  "typeCargo" : "BULK"
}, {
  "shipName" : "hCHPDxTFmeJpbDi",
  "tonnage" : 1057,
  "arrivalTime" : {
    "time" : 16643
  },
  "unloadTime" : {
    "time" : 53
  },
  "typeCargo" : "BULK"
}, {
  "shipName" : "OYfSiY]jFlMStbL",
  "tonnage" : 1086,
  "arrivalTime" : {
    "time" : 16650
  },
  "unloadTime" : {
    "time" : 55
  },
  "typeCargo" : "CONTAINER"
}, {
  "shipName" : "cA^StYJY`SgZQlL",
  "tonnage" : 1131,
  "arrivalTime" : {
    "time" : 16825
  },
  "unloadTime" : {
    "time" : 57
  },
  "typeCargo" : "LIQUID"
}, {
  "shipName" : "ITFVUhaXNWiPVUB",
  "tonnage" : 1165,
  "arrivalTime" : {
    "time" : 17193
  },
  "unloadTime" : {
    "time" : 59
  },
  "typeCargo" : "LIQUID"
}, {
  "shipName" : "l`kQRpQ_rUjWPJH",
  "tonnage" : 1042,
  "arrivalTime" : {
    "time" : 17544
  },
  "unloadTime" : {
    "time" : 53
  },
  "typeCargo" : "LIQUID"
}, {
  "shipName" : "fKecaVUS_LUhVtH",
  "tonnage" : 1197,
  "arrivalTime" : {
    "time" : 17570
  },
  "unloadTime" : {
    "time" : 60
  },
  "typeCargo" : "BULK"
}, {
  "shipName" : "FUr^ZeSfPaGJJ[\\",
  "tonnage" : 1088,
  "arrivalTime" : {
    "time" : 17859
  },
  "unloadTime" : {
    "time" : 55
  },
  "typeCargo" : "LIQUID"
}, {
  "shipName" : "`pPEJqFaLUIV[YY",
  "tonnage" : 969,
  "arrivalTime" : {
    "time" : 17897
  },
  "unloadTime" : {
    "time" : 49
  },
  "typeCargo" : "LIQUID"
}, {
  "shipName" : "QeiSRATrUvIkOQK",
  "tonnage" : 962,
  "arrivalTime" : {
    "time" : 18123
  },
  "unloadTime" : {
    "time" : 49
  },
  "typeCargo" : "CONTAINER"
}, {
  "shipName" : "\\]VVGtkTWnMKkem",
  "tonnage" : 965,
  "arrivalTime" : {
    "time" : 18440
  },
  "unloadTime" : {
    "time" : 49
  },
  "typeCargo" : "LIQUID"
}, {
  "shipName" : "cIWZTT`FDTSgATT",
  "tonnage" : 1172,
  "arrivalTime" : {
    "time" : 18549
  },
  "unloadTime" : {
    "time" : 59
  },
  "typeCargo" : "LIQUID"
}, {
  "shipName" : "NZdZdEVahHVPKAC",
  "tonnage" : 969,
  "arrivalTime" : {
    "time" : 18733
  },
  "unloadTime" : {
    "time" : 49
  },
  "typeCargo" : "BULK"
}, {
  "shipName" : "UlbPDKISVRhakXW",
  "tonnage" : 945,
  "arrivalTime" : {
    "time" : 18902
  },
  "unloadTime" : {
    "time" : 48
  },
  "typeCargo" : "LIQUID"
}, {
  "shipName" : "UcHfYiVVTR]KXUV",
  "tonnage" : 1126,
  "arrivalTime" : {
    "time" : 19041
  },
  "unloadTime" : {
    "time" : 57
  },
  "typeCargo" : "CONTAINER"
}, {
  "shipName" : "[Sj]rZVargea[rZ",
  "tonnage" : 1157,
  "arrivalTime" : {
    "time" : 19050
  },
  "unloadTime" : {
    "time" : 58
  },
  "typeCargo" : "CONTAINER"
}, {
  "shipName" : "ZDP\\D\\LeOeaUMDL",
  "tonnage" : 925,
  "arrivalTime" : {
    "time" : 19103
  },
  "unloadTime" : {
    "time" : 47
  },
  "typeCargo" : "LIQUID"
}, {
  "shipName" : "YVkfMn^AENQdiB_",
  "tonnage" : 1072,
  "arrivalTime" : {
    "time" : 19245
  },
  "unloadTime" : {
    "time" : 54
  },
  "typeCargo" : "BULK"
}, {
  "shipName" : "XjyWPWWnV[JbhW]",
  "tonnage" : 1086,
  "arrivalTime" : {
    "time" : 19289
  },
  "unloadTime" : {
    "time" : 55
  },
  "typeCargo" : "CONTAINER"
}, {
  "shipName" : "T`WVHkSiQGPDVOu",
  "tonnage" : 1058,
  "arrivalTime" : {
    "time" : 19319
  },
  "unloadTime" : {
    "time" : 53
  },
  "typeCargo" : "BULK"
}, {
  "shipName" : "OHam`_TKPBJBJtE",
  "tonnage" : 964,
  "arrivalTime" : {
    "time" : 19401
  },
  "unloadTime" : {
    "time" : 49
  },
  "typeCargo" : "BULK"
}, {
  "shipName" : "cTTJFXhyV[uvaQ_",
  "tonnage" : 1154,
  "arrivalTime" : {
    "time" : 19601
  },
  "unloadTime" : {
    "time" : 58
  },
  "typeCargo" : "CONTAINER"
}, {
  "shipName" : "AHGLYHSUA\\A^SPL",
  "tonnage" : 1025,
  "arrivalTime" : {
    "time" : 19933
  },
  "unloadTime" : {
    "time" : 52
  },
  "typeCargo" : "LIQUID"
}, {
  "shipName" : "D`XXBWUaf]]dR]c",
  "tonnage" : 903,
  "arrivalTime" : {
    "time" : 20090
  },
  "unloadTime" : {
    "time" : 46
  },
  "typeCargo" : "BULK"
}, {
  "shipName" : "UdUbIpEl`J[ERiX",
  "tonnage" : 1137,
  "arrivalTime" : {
    "time" : 20480
  },
  "unloadTime" : {
    "time" : 57
  },
  "typeCargo" : "LIQUID"
}, {
  "shipName" : "IfXcLXCTYHQRaXg",
  "tonnage" : 915,
  "arrivalTime" : {
    "time" : 20505
  },
  "unloadTime" : {
    "time" : 46
  },
  "typeCargo" : "BULK"
}, {
  "shipName" : "EgAlXpEfEAFEHC`",
  "tonnage" : 1097,
  "arrivalTime" : {
    "time" : 20540
  },
  "unloadTime" : {
    "time" : 55
  },
  "typeCargo" : "LIQUID"
}, {
  "shipName" : "J_kCLbn\\[EGgDPZ",
  "tonnage" : 1040,
  "arrivalTime" : {
    "time" : 20788
  },
  "unloadTime" : {
    "time" : 52
  },
  "typeCargo" : "BULK"
}, {
  "shipName" : "djZT`UPUUTaLNhi",
  "tonnage" : 927,
  "arrivalTime" : {
    "time" : 20867
  },
  "unloadTime" : {
    "time" : 47
  },
  "typeCargo" : "BULK"
}, {
  "shipName" : "[bFajE[NMfijUQ`",
  "tonnage" : 1097,
  "arrivalTime" : {
    "time" : 21070
  },
  "unloadTime" : {
    "time" : 55
  },
  "typeCargo" : "CONTAINER"
}, {
  "shipName" : "DQGU`Y]NQFPOLbA",
  "tonnage" : 968,
  "arrivalTime" : {
    "time" : 21167
  },
  "unloadTime" : {
    "time" : 49
  },
  "typeCargo" : "CONTAINER"
}, {
  "shipName" : "OOvQ_BKPNmSYQ`G",
  "tonnage" : 1118,
  "arrivalTime" : {
    "time" : 21340
  },
  "unloadTime" : {
    "time" : 56
  },
  "typeCargo" : "LIQUID"
}, {
  "shipName" : "JWGH^T`W]CbgRqL",
  "tonnage" : 1044,
  "arrivalTime" : {
    "time" : 21393
  },
  "unloadTime" : {
    "time" : 53
  },
  "typeCargo" : "LIQUID"
}, {
  "shipName" : "Ql_btW]WGtgXK`F",
  "tonnage" : 979,
  "arrivalTime" : {
    "time" : 21427
  },
  "unloadTime" : {
    "time" : 49
  },
  "typeCargo" : "BULK"
}, {
  "shipName" : "ETaKBOVUSJPTdQM",
  "tonnage" : 1139,
  "arrivalTime" : {
    "time" : 21587
  },
  "unloadTime" : {
    "time" : 57
  },
  "typeCargo" : "BULK"
}, {
  "shipName" : "YGPUfOVMCB`IBeH",
  "tonnage" : 951,
  "arrivalTime" : {
    "time" : 21708
  },
  "unloadTime" : {
    "time" : 48
  },
  "typeCargo" : "LIQUID"
}, {
  "shipName" : "afmjOnNoSTU[rOa",
  "tonnage" : 954,
  "arrivalTime" : {
    "time" : 21743
  },
  "unloadTime" : {
    "time" : 48
  },
  "typeCargo" : "CONTAINER"
}, {
  "shipName" : "IZOwjfvGLYpYerT",
  "tonnage" : 949,
  "arrivalTime" : {
    "time" : 21786
  },
  "unloadTime" : {
    "time" : 48
  },
  "typeCargo" : "BULK"
}, {
  "shipName" : "qdZQZZXQWJnH`iM",
  "tonnage" : 985,
  "arrivalTime" : {
    "time" : 21844
  },
  "unloadTime" : {
    "time" : 50
  },
  "typeCargo" : "LIQUID"
}, {
  "shipName" : "V\\PQfofenCIJB_Y",
  "tonnage" : 1055,
  "arrivalTime" : {
    "time" : 21873
  },
  "unloadTime" : {
    "time" : 53
  },
  "typeCargo" : "CONTAINER"
}, {
  "shipName" : "GdQFkjbWaPQ`_hc",
  "tonnage" : 1007,
  "arrivalTime" : {
    "time" : 21988
  },
  "unloadTime" : {
    "time" : 51
  },
  "typeCargo" : "CONTAINER"
}, {
  "shipName" : "ABBW]gFmXLtfCaI",
  "tonnage" : 941,
  "arrivalTime" : {
    "time" : 22076
  },
  "unloadTime" : {
    "time" : 48
  },
  "typeCargo" : "LIQUID"
}, {
  "shipName" : "ZXPIIGRBGYfXSTd",
  "tonnage" : 1131,
  "arrivalTime" : {
    "time" : 22260
  },
  "unloadTime" : {
    "time" : 57
  },
  "typeCargo" : "CONTAINER"
}, {
  "shipName" : "TfSRra_CmNKqXcF",
  "tonnage" : 1051,
  "arrivalTime" : {
    "time" : 22440
  },
  "unloadTime" : {
    "time" : 53
  },
  "typeCargo" : "CONTAINER"
}, {
  "shipName" : "o_[XaKVQ^eWJe\\T",
  "tonnage" : 924,
  "arrivalTime" : {
    "time" : 22459
  },
  "unloadTime" : {
    "time" : 47
  },
  "typeCargo" : "BULK"
}, {
  "shipName" : "N]qHBFcDRFYFbey",
  "tonnage" : 1038,
  "arrivalTime" : {
    "time" : 22509
  },
  "unloadTime" : {
    "time" : 52
  },
  "typeCargo" : "CONTAINER"
}, {
  "shipName" : "K_vISKK]YJaKVGS",
  "tonnage" : 935,
  "arrivalTime" : {
    "time" : 22536
  },
  "unloadTime" : {
    "time" : 47
  },
  "typeCargo" : "LIQUID"
}, {
  "shipName" : "MiHDfXZXoDaBAVZ",
  "tonnage" : 1120,
  "arrivalTime" : {
    "time" : 23687
  },
  "unloadTime" : {
    "time" : 56
  },
  "typeCargo" : "LIQUID"
}, {
  "shipName" : "mjGqrdVD`PYaZPL",
  "tonnage" : 1082,
  "arrivalTime" : {
    "time" : 23739
  },
  "unloadTime" : {
    "time" : 55
  },
  "typeCargo" : "BULK"
}, {
  "shipName" : "iZVGleSOZcvOY[T",
  "tonnage" : 1168,
  "arrivalTime" : {
    "time" : 23868
  },
  "unloadTime" : {
    "time" : 59
  },
  "typeCargo" : "BULK"
}, {
  "shipName" : "kZHBfXZeRcUESRY",
  "tonnage" : 1020,
  "arrivalTime" : {
    "time" : 24022
  },
  "unloadTime" : {
    "time" : 51
  },
  "typeCargo" : "CONTAINER"
}, {
  "shipName" : "YWGBWEqVYQWUYH`",
  "tonnage" : 983,
  "arrivalTime" : {
    "time" : 24211
  },
  "unloadTime" : {
    "time" : 50
  },
  "typeCargo" : "BULK"
}, {
  "shipName" : "_[VfWCLaSTylQOD",
  "tonnage" : 1092,
  "arrivalTime" : {
    "time" : 24354
  },
  "unloadTime" : {
    "time" : 55
  },
  "typeCargo" : "BULK"
}, {
  "shipName" : "XfO^aY]NoMSNZoG",
  "tonnage" : 961,
  "arrivalTime" : {
    "time" : 24756
  },
  "unloadTime" : {
    "time" : 49
  },
  "typeCargo" : "LIQUID"
}, {
  "shipName" : "YYcZdUOeWA`WQhc",
  "tonnage" : 944,
  "arrivalTime" : {
    "time" : 24948
  },
  "unloadTime" : {
    "time" : 48
  },
  "typeCargo" : "LIQUID"
}, {
  "shipName" : "PPSANHPtJOlKebc",
  "tonnage" : 1072,
  "arrivalTime" : {
    "time" : 25037
  },
  "unloadTime" : {
    "time" : 54
  },
  "typeCargo" : "CONTAINER"
}, {
  "shipName" : "T]bZJTJxCd`JIgN",
  "tonnage" : 1143,
  "arrivalTime" : {
    "time" : 25094
  },
  "unloadTime" : {
    "time" : 58
  },
  "typeCargo" : "BULK"
}, {
  "shipName" : "ZXdYpOANYcPRoFF",
  "tonnage" : 1101,
  "arrivalTime" : {
    "time" : 25194
  },
  "unloadTime" : {
    "time" : 56
  },
  "typeCargo" : "CONTAINER"
}, {
  "shipName" : "NfqbpkVM[HRO`bK",
  "tonnage" : 1029,
  "arrivalTime" : {
    "time" : 25198
  },
  "unloadTime" : {
    "time" : 52
  },
  "typeCargo" : "LIQUID"
}, {
  "shipName" : "hUHKTiMQ_ScGUAg",
  "tonnage" : 1008,
  "arrivalTime" : {
    "time" : 25236
  },
  "unloadTime" : {
    "time" : 51
  },
  "typeCargo" : "CONTAINER"
}, {
  "shipName" : "p^OVAPZEYbqNQ[m",
  "tonnage" : 1023,
  "arrivalTime" : {
    "time" : 25273
  },
  "unloadTime" : {
    "time" : 52
  },
  "typeCargo" : "LIQUID"
}, {
  "shipName" : "DbCHILG]NJ_VSOM",
  "tonnage" : 1103,
  "arrivalTime" : {
    "time" : 25293
  },
  "unloadTime" : {
    "time" : 56
  },
  "typeCargo" : "CONTAINER"
}, {
  "shipName" : "QY\\HOU]R\\GORdhA",
  "tonnage" : 972,
  "arrivalTime" : {
    "time" : 25536
  },
  "unloadTime" : {
    "time" : 49
  },
  "typeCargo" : "CONTAINER"
}, {
  "shipName" : "YCEh`ZXUdVSQI[f",
  "tonnage" : 1035,
  "arrivalTime" : {
    "time" : 25552
  },
  "unloadTime" : {
    "time" : 52
  },
  "typeCargo" : "BULK"
}, {
  "shipName" : "RerdRPaOnZzZdRR",
  "tonnage" : 1163,
  "arrivalTime" : {
    "time" : 25555
  },
  "unloadTime" : {
    "time" : 59
  },
  "typeCargo" : "BULK"
}, {
  "shipName" : "GoKEOkQSn^DRAQb",
  "tonnage" : 1072,
  "arrivalTime" : {
    "time" : 25644
  },
  "unloadTime" : {
    "time" : 54
  },
  "typeCargo" : "LIQUID"
}, {
  "shipName" : "XYUHcCYnZHdEboX",
  "tonnage" : 1062,
  "arrivalTime" : {
    "time" : 25677
  },
  "unloadTime" : {
    "time" : 54
  },
  "typeCargo" : "CONTAINER"
}, {
  "shipName" : "RIHcVPMbS^DBUHk",
  "tonnage" : 978,
  "arrivalTime" : {
    "time" : 26061
  },
  "unloadTime" : {
    "time" : 49
  },
  "typeCargo" : "BULK"
}, {
  "shipName" : "UKgTHdaYG_HWIIN",
  "tonnage" : 927,
  "arrivalTime" : {
    "time" : 26343
  },
  "unloadTime" : {
    "time" : 47
  },
  "typeCargo" : "LIQUID"
}, {
  "shipName" : "n\\QOIMhJTLaiOMX",
  "tonnage" : 992,
  "arrivalTime" : {
    "time" : 26449
  },
  "unloadTime" : {
    "time" : 50
  },
  "typeCargo" : "CONTAINER"
}, {
  "shipName" : "ISOe^UkkvNJUOM]",
  "tonnage" : 1042,
  "arrivalTime" : {
    "time" : 26851
  },
  "unloadTime" : {
    "time" : 53
  },
  "typeCargo" : "LIQUID"
}, {
  "shipName" : "Jd^]lNjXHocuPQY",
  "tonnage" : 1035,
  "arrivalTime" : {
    "time" : 26853
  },
  "unloadTime" : {
    "time" : 52
  },
  "typeCargo" : "CONTAINER"
}, {
  "shipName" : "^lHYZKFSZSYBJ^s",
  "tonnage" : 913,
  "arrivalTime" : {
    "time" : 27060
  },
  "unloadTime" : {
    "time" : 46
  },
  "typeCargo" : "BULK"
}, {
  "shipName" : "NSqn\\zMBqa]aWVv",
  "tonnage" : 919,
  "arrivalTime" : {
    "time" : 27170
  },
  "unloadTime" : {
    "time" : 46
  },
  "typeCargo" : "BULK"
}, {
  "shipName" : "V\\SEfi\\LREPNFbe",
  "tonnage" : 1177,
  "arrivalTime" : {
    "time" : 27456
  },
  "unloadTime" : {
    "time" : 59
  },
  "typeCargo" : "LIQUID"
}, {
  "shipName" : "SCECsBWQFeWo[fg",
  "tonnage" : 996,
  "arrivalTime" : {
    "time" : 27565
  },
  "unloadTime" : {
    "time" : 50
  },
  "typeCargo" : "LIQUID"
}, {
  "shipName" : "dleKIZ]LnPdAuKS",
  "tonnage" : 949,
  "arrivalTime" : {
    "time" : 27979
  },
  "unloadTime" : {
    "time" : 48
  },
  "typeCargo" : "CONTAINER"
}, {
  "shipName" : "OTGb_uXLH_XJk`K",
  "tonnage" : 1071,
  "arrivalTime" : {
    "time" : 28320
  },
  "unloadTime" : {
    "time" : 54
  },
  "typeCargo" : "CONTAINER"
}, {
  "shipName" : "TocE\\PgKXiqNdb\\",
  "tonnage" : 921,
  "arrivalTime" : {
    "time" : 28478
  },
  "unloadTime" : {
    "time" : 47
  },
  "typeCargo" : "LIQUID"
}, {
  "shipName" : "YfLTJQWelI]^iZP",
  "tonnage" : 988,
  "arrivalTime" : {
    "time" : 28544
  },
  "unloadTime" : {
    "time" : 50
  },
  "typeCargo" : "BULK"
}, {
  "shipName" : "YmOd\\wvYPVOgZNZ",
  "tonnage" : 988,
  "arrivalTime" : {
    "time" : 28565
  },
  "unloadTime" : {
    "time" : 50
  },
  "typeCargo" : "BULK"
}, {
  "shipName" : "fcVJXTFJMXmvH`R",
  "tonnage" : 1156,
  "arrivalTime" : {
    "time" : 28740
  },
  "unloadTime" : {
    "time" : 58
  },
  "typeCargo" : "LIQUID"
}, {
  "shipName" : "aOhnX_XlL_gOkYJ",
  "tonnage" : 1170,
  "arrivalTime" : {
    "time" : 28769
  },
  "unloadTime" : {
    "time" : 59
  },
  "typeCargo" : "CONTAINER"
}, {
  "shipName" : "\\NBRYZkBIRWhKYE",
  "tonnage" : 1042,
  "arrivalTime" : {
    "time" : 28969
  },
  "unloadTime" : {
    "time" : 53
  },
  "typeCargo" : "LIQUID"
}, {
  "shipName" : "RK\\fQCdXm\\BDgUK",
  "tonnage" : 1128,
  "arrivalTime" : {
    "time" : 29269
  },
  "unloadTime" : {
    "time" : 57
  },
  "typeCargo" : "CONTAINER"
}, {
  "shipName" : "LEVHTO]VG]On^^O",
  "tonnage" : 994,
  "arrivalTime" : {
    "time" : 29496
  },
  "unloadTime" : {
    "time" : 50
  },
  "typeCargo" : "BULK"
}, {
  "shipName" : "OKXMCJWQ\\rdf_KG",
  "tonnage" : 1004,
  "arrivalTime" : {
    "time" : 29596
  },
  "unloadTime" : {
    "time" : 51
  },
  "typeCargo" : "LIQUID"
}, {
  "shipName" : "ZEK]WUWMF_JTj_c",
  "tonnage" : 1026,
  "arrivalTime" : {
    "time" : 29613
  },
  "unloadTime" : {
    "time" : 52
  },
  "typeCargo" : "BULK"
}, {
  "shipName" : "Xl]XaO^CJKZEHNT",
  "tonnage" : 1126,
  "arrivalTime" : {
    "time" : 29833
  },
  "unloadTime" : {
    "time" : 57
  },
  "typeCargo" : "LIQUID"
}, {
  "shipName" : "EJaRSOjUNaIIJDU",
  "tonnage" : 1158,
  "arrivalTime" : {
    "time" : 30090
  },
  "unloadTime" : {
    "time" : 58
  },
  "typeCargo" : "BULK"
}, {
  "shipName" : "SauWjRfYTLPDTlT",
  "tonnage" : 1091,
  "arrivalTime" : {
    "time" : 30099
  },
  "unloadTime" : {
    "time" : 55
  },
  "typeCargo" : "CONTAINER"
}, {
  "shipName" : "V[cIV_TSrhXEkSh",
  "tonnage" : 1170,
  "arrivalTime" : {
    "time" : 30101
  },
  "unloadTime" : {
    "time" : 59
  },
  "typeCargo" : "BULK"
}, {
  "shipName" : "hZncQ[ZUKfVaDKC",
  "tonnage" : 1090,
  "arrivalTime" : {
    "time" : 30126
  },
  "unloadTime" : {
    "time" : 55
  },
  "typeCargo" : "BULK"
}, {
  "shipName" : "`NWgElYMlEWCg`N",
  "tonnage" : 1024,
  "arrivalTime" : {
    "time" : 30277
  },
  "unloadTime" : {
    "time" : 52
  },
  "typeCargo" : "CONTAINER"
}, {
  "shipName" : "p]GnJABLgaLUdnY",
  "tonnage" : 917,
  "arrivalTime" : {
    "time" : 30318
  },
  "unloadTime" : {
    "time" : 46
  },
  "typeCargo" : "LIQUID"
}, {
  "shipName" : "AFuuIISVeNfJSPm",
  "tonnage" : 1095,
  "arrivalTime" : {
    "time" : 30442
  },
  "unloadTime" : {
    "time" : 55
  },
  "typeCargo" : "BULK"
}, {
  "shipName" : "B`b\\t^iDRUSAnOG",
  "tonnage" : 973,
  "arrivalTime" : {
    "time" : 30560
  },
  "unloadTime" : {
    "time" : 49
  },
  "typeCargo" : "BULK"
}, {
  "shipName" : "MPLNuTIBQDOdGA[",
  "tonnage" : 1078,
  "arrivalTime" : {
    "time" : 31214
  },
  "unloadTime" : {
    "time" : 54
  },
  "typeCargo" : "CONTAINER"
}, {
  "shipName" : "PYW[ALXWXXX^WmJ",
  "tonnage" : 1096,
  "arrivalTime" : {
    "time" : 31400
  },
  "unloadTime" : {
    "time" : 55
  },
  "typeCargo" : "BULK"
}, {
  "shipName" : "emRvBfRddMmlYcF",
  "tonnage" : 1057,
  "arrivalTime" : {
    "time" : 31436
  },
  "unloadTime" : {
    "time" : 53
  },
  "typeCargo" : "CONTAINER"
}, {
  "shipName" : "UUcSsadLgZS]`c[",
  "tonnage" : 1167,
  "arrivalTime" : {
    "time" : 31523
  },
  "unloadTime" : {
    "time" : 59
  },
  "typeCargo" : "BULK"
}, {
  "shipName" : "gVd]PmVoCKYlKNW",
  "tonnage" : 1160,
  "arrivalTime" : {
    "time" : 31677
  },
  "unloadTime" : {
    "time" : 58
  },
  "typeCargo" : "BULK"
}, {
  "shipName" : "VaABfOCHJVXu`RS",
  "tonnage" : 1055,
  "arrivalTime" : {
    "time" : 31760
  },
  "unloadTime" : {
    "time" : 53
  },
  "typeCargo" : "LIQUID"
}, {
  "shipName" : "aLLLsNQ[nCKBP_P",
  "tonnage" : 1111,
  "arrivalTime" : {
    "time" : 31801
  },
  "unloadTime" : {
    "time" : 56
  },
  "typeCargo" : "BULK"
}, {
  "shipName" : "se`BOMVHWC]hL\\w",
  "tonnage" : 1059,
  "arrivalTime" : {
    "time" : 31915
  },
  "unloadTime" : {
    "time" : 53
  },
  "typeCargo" : "LIQUID"
}, {
  "shipName" : "YZGCgiR[XHG\\fOU",
  "tonnage" : 926,
  "arrivalTime" : {
    "time" : 32024
  },
  "unloadTime" : {
    "time" : 47
  },
  "typeCargo" : "CONTAINER"
}, {
  "shipName" : "pXcRTVWOSGeJZfJ",
  "tonnage" : 1091,
  "arrivalTime" : {
    "time" : 32102
  },
  "unloadTime" : {
    "time" : 55
  },
  "typeCargo" : "CONTAINER"
}, {
  "shipName" : "JWhVqT[RBEh]tMM",
  "tonnage" : 1150,
  "arrivalTime" : {
    "time" : 32120
  },
  "unloadTime" : {
    "time" : 58
  },
  "typeCargo" : "LIQUID"
}, {
  "shipName" : "TY`^VOLQPHL^cAR",
  "tonnage" : 922,
  "arrivalTime" : {
    "time" : 32214
  },
  "unloadTime" : {
    "time" : 47
  },
  "typeCargo" : "BULK"
}, {
  "shipName" : "XUcOAccTZXWn`OJ",
  "tonnage" : 941,
  "arrivalTime" : {
    "time" : 32318
  },
  "unloadTime" : {
    "time" : 48
  },
  "typeCargo" : "CONTAINER"
}, {
  "shipName" : "THBPeP`UdvPoiR`",
  "tonnage" : 922,
  "arrivalTime" : {
    "time" : 32469
  },
  "unloadTime" : {
    "time" : 47
  },
  "typeCargo" : "CONTAINER"
}, {
  "shipName" : "LXXNOZRKCWmkIF`",
  "tonnage" : 1138,
  "arrivalTime" : {
    "time" : 32475
  },
  "unloadTime" : {
    "time" : 57
  },
  "typeCargo" : "CONTAINER"
}, {
  "shipName" : "V[UZlKUbIC\\JU[X",
  "tonnage" : 1107,
  "arrivalTime" : {
    "time" : 32554
  },
  "unloadTime" : {
    "time" : 56
  },
  "typeCargo" : "CONTAINER"
}, {
  "shipName" : "PcPVRXydFlRkYmW",
  "tonnage" : 968,
  "arrivalTime" : {
    "time" : 32585
  },
  "unloadTime" : {
    "time" : 49
  },
  "typeCargo" : "BULK"
}, {
  "shipName" : "ZQGgDekCERTFLMs",
  "tonnage" : 993,
  "arrivalTime" : {
    "time" : 32838
  },
  "unloadTime" : {
    "time" : 50
  },
  "typeCargo" : "LIQUID"
}, {
  "shipName" : "BWLPiXUkRV`Vp]g",
  "tonnage" : 1105,
  "arrivalTime" : {
    "time" : 32866
  },
  "unloadTime" : {
    "time" : 56
  },
  "typeCargo" : "BULK"
}, {
  "shipName" : "USbXccGheLPUV\\Y",
  "tonnage" : 1020,
  "arrivalTime" : {
    "time" : 32965
  },
  "unloadTime" : {
    "time" : 51
  },
  "typeCargo" : "CONTAINER"
}, {
  "shipName" : "TWIVlM\\dIam[dCY",
  "tonnage" : 1140,
  "arrivalTime" : {
    "time" : 33045
  },
  "unloadTime" : {
    "time" : 57
  },
  "typeCargo" : "CONTAINER"
}, {
  "shipName" : "IXCdXbrSlI_uaTW",
  "tonnage" : 962,
  "arrivalTime" : {
    "time" : 33424
  },
  "unloadTime" : {
    "time" : 49
  },
  "typeCargo" : "CONTAINER"
}, {
  "shipName" : "BeKqNcaPHbcONP_",
  "tonnage" : 1153,
  "arrivalTime" : {
    "time" : 33757
  },
  "unloadTime" : {
    "time" : 58
  },
  "typeCargo" : "CONTAINER"
}, {
  "shipName" : "LMVSN_Yc\\]ncNih",
  "tonnage" : 1082,
  "arrivalTime" : {
    "time" : 33781
  },
  "unloadTime" : {
    "time" : 55
  },
  "typeCargo" : "CONTAINER"
}, {
  "shipName" : "dQjST`cng_NnPAL",
  "tonnage" : 1010,
  "arrivalTime" : {
    "time" : 34172
  },
  "unloadTime" : {
    "time" : 51
  },
  "typeCargo" : "LIQUID"
}, {
  "shipName" : "TOXUhDPHZm`QadP",
  "tonnage" : 902,
  "arrivalTime" : {
    "time" : 34304
  },
  "unloadTime" : {
    "time" : 46
  },
  "typeCargo" : "CONTAINER"
}, {
  "shipName" : "]PGhWEZRWo^ydQI",
  "tonnage" : 1100,
  "arrivalTime" : {
    "time" : 34438
  },
  "unloadTime" : {
    "time" : 55
  },
  "typeCargo" : "BULK"
}, {
  "shipName" : "GQWbHAd[ILVdVMQ",
  "tonnage" : 1091,
  "arrivalTime" : {
    "time" : 34438
  },
  "unloadTime" : {
    "time" : 55
  },
  "typeCargo" : "LIQUID"
}, {
  "shipName" : "[`feSN]cYnLMWLB",
  "tonnage" : 1128,
  "arrivalTime" : {
    "time" : 34569
  },
  "unloadTime" : {
    "time" : 57
  },
  "typeCargo" : "LIQUID"
}, {
  "shipName" : "Xm]CVV[D^_ZBPDP",
  "tonnage" : 1093,
  "arrivalTime" : {
    "time" : 34589
  },
  "unloadTime" : {
    "time" : 55
  },
  "typeCargo" : "LIQUID"
}, {
  "shipName" : "AiJWSUINZdTxTTU",
  "tonnage" : 975,
  "arrivalTime" : {
    "time" : 34632
  },
  "unloadTime" : {
    "time" : 49
  },
  "typeCargo" : "LIQUID"
}, {
  "shipName" : "Ra_MjbQ]GQYVFxF",
  "tonnage" : 1018,
  "arrivalTime" : {
    "time" : 34729
  },
  "unloadTime" : {
    "time" : 51
  },
  "typeCargo" : "LIQUID"
}, {
  "shipName" : "URIaDMUgh]NwZ^f",
  "tonnage" : 1177,
  "arrivalTime" : {
    "time" : 34738
  },
  "unloadTime" : {
    "time" : 59
  },
  "typeCargo" : "LIQUID"
}, {
  "shipName" : "UIP`bYRmYMsZQZq",
  "tonnage" : 1030,
  "arrivalTime" : {
    "time" : 35050
  },
  "unloadTime" : {
    "time" : 52
  },
  "typeCargo" : "CONTAINER"
}, {
  "shipName" : "[mBXEhBkcYVGVHJ",
  "tonnage" : 1166,
  "arrivalTime" : {
    "time" : 35084
  },
  "unloadTime" : {
    "time" : 59
  },
  "typeCargo" : "BULK"
}, {
  "shipName" : "H\\kQF[ZJZkLJJLW",
  "tonnage" : 1048,
  "arrivalTime" : {
    "time" : 35134
  },
  "unloadTime" : {
    "time" : 53
  },
  "typeCargo" : "CONTAINER"
}, {
  "shipName" : "VHG\\\\iJ\\N]ZfkaQ",
  "tonnage" : 988,
  "arrivalTime" : {
    "time" : 35183
  },
  "unloadTime" : {
    "time" : 50
  },
  "typeCargo" : "BULK"
}, {
  "shipName" : "YcFLrNMj[ku^BQh",
  "tonnage" : 1145,
  "arrivalTime" : {
    "time" : 35272
  },
  "unloadTime" : {
    "time" : 58
  },
  "typeCargo" : "BULK"
}, {
  "shipName" : "BGGNfQOUZ``N^WH",
  "tonnage" : 997,
  "arrivalTime" : {
    "time" : 35350
  },
  "unloadTime" : {
    "time" : 50
  },
  "typeCargo" : "BULK"
}, {
  "shipName" : "Zj_HHJXBLNb]g[_",
  "tonnage" : 1035,
  "arrivalTime" : {
    "time" : 35530
  },
  "unloadTime" : {
    "time" : 52
  },
  "typeCargo" : "LIQUID"
}, {
  "shipName" : "JXbWPBEYVPneloJ",
  "tonnage" : 1013,
  "arrivalTime" : {
    "time" : 35850
  },
  "unloadTime" : {
    "time" : 51
  },
  "typeCargo" : "LIQUID"
}, {
  "shipName" : "bPV]NPOZgUXORnh",
  "tonnage" : 1053,
  "arrivalTime" : {
    "time" : 35853
  },
  "unloadTime" : {
    "time" : 53
  },
  "typeCargo" : "CONTAINER"
}, {
  "shipName" : "pEXHAWxTOGRPGSo",
  "tonnage" : 951,
  "arrivalTime" : {
    "time" : 36061
  },
  "unloadTime" : {
    "time" : 48
  },
  "typeCargo" : "BULK"
}, {
  "shipName" : "[NAbflRshGaSN]l",
  "tonnage" : 939,
  "arrivalTime" : {
    "time" : 36159
  },
  "unloadTime" : {
    "time" : 47
  },
  "typeCargo" : "BULK"
}, {
  "shipName" : "SvGMhIVPENEjCM[",
  "tonnage" : 1152,
  "arrivalTime" : {
    "time" : 36218
  },
  "unloadTime" : {
    "time" : 58
  },
  "typeCargo" : "BULK"
}, {
  "shipName" : "AAFhXjL]IPOGISG",
  "tonnage" : 999,
  "arrivalTime" : {
    "time" : 36297
  },
  "unloadTime" : {
    "time" : 50
  },
  "typeCargo" : "CONTAINER"
}, {
  "shipName" : "VX_XTDMPRcuUCGT",
  "tonnage" : 1199,
  "arrivalTime" : {
    "time" : 36498
  },
  "unloadTime" : {
    "time" : 60
  },
  "typeCargo" : "CONTAINER"
}, {
  "shipName" : "AONXqceYj^cWuSK",
  "tonnage" : 1005,
  "arrivalTime" : {
    "time" : 36516
  },
  "unloadTime" : {
    "time" : 51
  },
  "typeCargo" : "LIQUID"
}, {
  "shipName" : "dYaFOVROXcbKRoU",
  "tonnage" : 1134,
  "arrivalTime" : {
    "time" : 36621
  },
  "unloadTime" : {
    "time" : 57
  },
  "typeCargo" : "LIQUID"
}, {
  "shipName" : "OKAZDRHWhGWTaMI",
  "tonnage" : 1015,
  "arrivalTime" : {
    "time" : 36753
  },
  "unloadTime" : {
    "time" : 51
  },
  "typeCargo" : "LIQUID"
}, {
  "shipName" : "^VPXPzEOXJaHWPO",
  "tonnage" : 1060,
  "arrivalTime" : {
    "time" : 36920
  },
  "unloadTime" : {
    "time" : 53
  },
  "typeCargo" : "LIQUID"
}, {
  "shipName" : "MobBBMDOYDPieGG",
  "tonnage" : 1091,
  "arrivalTime" : {
    "time" : 36930
  },
  "unloadTime" : {
    "time" : 55
  },
  "typeCargo" : "LIQUID"
}, {
  "shipName" : "MV^TYHDUUtK`Jl]",
  "tonnage" : 1051,
  "arrivalTime" : {
    "time" : 37002
  },
  "unloadTime" : {
    "time" : 53
  },
  "typeCargo" : "LIQUID"
}, {
  "shipName" : "hLjTAPje]XTYnUQ",
  "tonnage" : 950,
  "arrivalTime" : {
    "time" : 37003
  },
  "unloadTime" : {
    "time" : 48
  },
  "typeCargo" : "LIQUID"
}, {
  "shipName" : "P`\\jIPellHtGiBZ",
  "tonnage" : 946,
  "arrivalTime" : {
    "time" : 37064
  },
  "unloadTime" : {
    "time" : 48
  },
  "typeCargo" : "LIQUID"
}, {
  "shipName" : "bOJOTHtM^J\\_]NP",
  "tonnage" : 932,
  "arrivalTime" : {
    "time" : 37105
  },
  "unloadTime" : {
    "time" : 47
  },
  "typeCargo" : "BULK"
}, {
  "shipName" : "WJTfZlCbDNS^LKs",
  "tonnage" : 1186,
  "arrivalTime" : {
    "time" : 37250
  },
  "unloadTime" : {
    "time" : 60
  },
  "typeCargo" : "BULK"
}, {
  "shipName" : "N[XrcdYTiC[wLhV",
  "tonnage" : 1104,
  "arrivalTime" : {
    "time" : 37323
  },
  "unloadTime" : {
    "time" : 56
  },
  "typeCargo" : "CONTAINER"
}, {
  "shipName" : "^TN^hMWfaRBRZCX",
  "tonnage" : 987,
  "arrivalTime" : {
    "time" : 37392
  },
  "unloadTime" : {
    "time" : 50
  },
  "typeCargo" : "BULK"
}, {
  "shipName" : "`kMFCUbwAar\\CTY",
  "tonnage" : 1094,
  "arrivalTime" : {
    "time" : 37552
  },
  "unloadTime" : {
    "time" : 55
  },
  "typeCargo" : "CONTAINER"
}, {
  "shipName" : "tTfZHNThSTYW_WG",
  "tonnage" : 995,
  "arrivalTime" : {
    "time" : 37573
  },
  "unloadTime" : {
    "time" : 50
  },
  "typeCargo" : "BULK"
}, {
  "shipName" : "DxKLWTFjKxRqeQK",
  "tonnage" : 1081,
  "arrivalTime" : {
    "time" : 37618
  },
  "unloadTime" : {
    "time" : 55
  },
  "typeCargo" : "LIQUID"
}, {
  "shipName" : "TXbT`jW]X^gCt[y",
  "tonnage" : 1151,
  "arrivalTime" : {
    "time" : 37759
  },
  "unloadTime" : {
    "time" : 58
  },
  "typeCargo" : "LIQUID"
}, {
  "shipName" : "WJTbKUEMcqkgON_",
  "tonnage" : 959,
  "arrivalTime" : {
    "time" : 37813
  },
  "unloadTime" : {
    "time" : 48
  },
  "typeCargo" : "CONTAINER"
}, {
  "shipName" : "^eRdMoJZNNDZmLJ",
  "tonnage" : 1058,
  "arrivalTime" : {
    "time" : 37815
  },
  "unloadTime" : {
    "time" : 53
  },
  "typeCargo" : "CONTAINER"
}, {
  "shipName" : "NAXLOAaSfBeUjdC",
  "tonnage" : 1081,
  "arrivalTime" : {
    "time" : 38189
  },
  "unloadTime" : {
    "time" : 55
  },
  "typeCargo" : "CONTAINER"
}, {
  "shipName" : "aXPXDMlZCYMGOS`",
  "tonnage" : 1057,
  "arrivalTime" : {
    "time" : 38204
  },
  "unloadTime" : {
    "time" : 53
  },
  "typeCargo" : "BULK"
}, {
  "shipName" : "ZaZIfr_aMCR^TXN",
  "tonnage" : 1196,
  "arrivalTime" : {
    "time" : 38560
  },
  "unloadTime" : {
    "time" : 60
  },
  "typeCargo" : "BULK"
}, {
  "shipName" : "AJO\\HFjaKViRs^W",
  "tonnage" : 1104,
  "arrivalTime" : {
    "time" : 38616
  },
  "unloadTime" : {
    "time" : 56
  },
  "typeCargo" : "LIQUID"
}, {
  "shipName" : "TQIqMAlaluP\\QYO",
  "tonnage" : 1071,
  "arrivalTime" : {
    "time" : 38740
  },
  "unloadTime" : {
    "time" : 54
  },
  "typeCargo" : "CONTAINER"
}, {
  "shipName" : "W`TWQXLRAgDAQem",
  "tonnage" : 922,
  "arrivalTime" : {
    "time" : 38822
  },
  "unloadTime" : {
    "time" : 47
  },
  "typeCargo" : "CONTAINER"
}, {
  "shipName" : "UfC_]QL_TQLRdOS",
  "tonnage" : 1189,
  "arrivalTime" : {
    "time" : 38872
  },
  "unloadTime" : {
    "time" : 60
  },
  "typeCargo" : "LIQUID"
}, {
  "shipName" : "KP\\QA]KQRHVAEGD",
  "tonnage" : 926,
  "arrivalTime" : {
    "time" : 39073
  },
  "unloadTime" : {
    "time" : 47
  },
  "typeCargo" : "BULK"
}, {
  "shipName" : "PUTELDCW_W\\_FeI",
  "tonnage" : 1008,
  "arrivalTime" : {
    "time" : 39095
  },
  "unloadTime" : {
    "time" : 51
  },
  "typeCargo" : "LIQUID"
}, {
  "shipName" : "bAaaTSIPwkoVxeX",
  "tonnage" : 1009,
  "arrivalTime" : {
    "time" : 39145
  },
  "unloadTime" : {
    "time" : 51
  },
  "typeCargo" : "LIQUID"
}, {
  "shipName" : "\\MFFGHVEaMacfUL",
  "tonnage" : 1143,
  "arrivalTime" : {
    "time" : 39342
  },
  "unloadTime" : {
    "time" : 58
  },
  "typeCargo" : "CONTAINER"
}, {
  "shipName" : "GFJWLGK]VnThbFT",
  "tonnage" : 901,
  "arrivalTime" : {
    "time" : 39608
  },
  "unloadTime" : {
    "time" : 46
  },
  "typeCargo" : "CONTAINER"
}, {
  "shipName" : "Z`DLoMeG_H`IClG",
  "tonnage" : 906,
  "arrivalTime" : {
    "time" : 39820
  },
  "unloadTime" : {
    "time" : 46
  },
  "typeCargo" : "LIQUID"
}, {
  "shipName" : "WfARbggOnQSQFWI",
  "tonnage" : 1190,
  "arrivalTime" : {
    "time" : 40032
  },
  "unloadTime" : {
    "time" : 60
  },
  "typeCargo" : "CONTAINER"
}, {
  "shipName" : "H`UCTEPbCE_GRah",
  "tonnage" : 981,
  "arrivalTime" : {
    "time" : 40231
  },
  "unloadTime" : {
    "time" : 50
  },
  "typeCargo" : "CONTAINER"
}, {
  "shipName" : "eXPFRVLqNQVXMAh",
  "tonnage" : 1191,
  "arrivalTime" : {
    "time" : 40454
  },
  "unloadTime" : {
    "time" : 60
  },
  "typeCargo" : "BULK"
}, {
  "shipName" : "cZKVQPTZkATMTPn",
  "tonnage" : 914,
  "arrivalTime" : {
    "time" : 40480
  },
  "unloadTime" : {
    "time" : 46
  },
  "typeCargo" : "LIQUID"
}, {
  "shipName" : "NiOpYGSmdS^]HZd",
  "tonnage" : 1155,
  "arrivalTime" : {
    "time" : 40650
  },
  "unloadTime" : {
    "time" : 58
  },
  "typeCargo" : "CONTAINER"
}, {
  "shipName" : "nSYNpBTNGXOXKZi",
  "tonnage" : 1004,
  "arrivalTime" : {
    "time" : 40910
  },
  "unloadTime" : {
    "time" : 51
  },
  "typeCargo" : "LIQUID"
}, {
  "shipName" : "qXV]``\\QMW_GUIQ",
  "tonnage" : 1180,
  "arrivalTime" : {
    "time" : 40984
  },
  "unloadTime" : {
    "time" : 59
  },
  "typeCargo" : "CONTAINER"
}, {
  "shipName" : "^F_UGXFoQHdt\\kN",
  "tonnage" : 1046,
  "arrivalTime" : {
    "time" : 41390
  },
  "unloadTime" : {
    "time" : 53
  },
  "typeCargo" : "LIQUID"
}, {
  "shipName" : "UJh`vNRxQIMU]nU",
  "tonnage" : 971,
  "arrivalTime" : {
    "time" : 41392
  },
  "unloadTime" : {
    "time" : 49
  },
  "typeCargo" : "LIQUID"
}, {
  "shipName" : "DON]FJVATJVUOHW",
  "tonnage" : 1188,
  "arrivalTime" : {
    "time" : 41393
  },
  "unloadTime" : {
    "time" : 60
  },
  "typeCargo" : "LIQUID"
}, {
  "shipName" : "QYOYOCPPZOMFUnX",
  "tonnage" : 1034,
  "arrivalTime" : {
    "time" : 41402
  },
  "unloadTime" : {
    "time" : 52
  },
  "typeCargo" : "LIQUID"
}, {
  "shipName" : "^drWkHWcBMZG\\gR",
  "tonnage" : 1192,
  "arrivalTime" : {
    "time" : 41555
  },
  "unloadTime" : {
    "time" : 60
  },
  "typeCargo" : "BULK"
}, {
  "shipName" : "ZIAEbWNPdSJPQHX",
  "tonnage" : 1016,
  "arrivalTime" : {
    "time" : 41649
  },
  "unloadTime" : {
    "time" : 51
  },
  "typeCargo" : "BULK"
}, {
  "shipName" : "TOv`OMQTVQKlrXY",
  "tonnage" : 934,
  "arrivalTime" : {
    "time" : 41662
  },
  "unloadTime" : {
    "time" : 47
  },
  "typeCargo" : "LIQUID"
}, {
  "shipName" : "Pw[UqdjdFXeenDf",
  "tonnage" : 1030,
  "arrivalTime" : {
    "time" : 41763
  },
  "unloadTime" : {
    "time" : 52
  },
  "typeCargo" : "LIQUID"
}, {
  "shipName" : "WSm[SINCC_O]THD",
  "tonnage" : 1055,
  "arrivalTime" : {
    "time" : 42104
  },
  "unloadTime" : {
    "time" : 53
  },
  "typeCargo" : "BULK"
}, {
  "shipName" : "m_T`LPCcDq]ec`d",
  "tonnage" : 933,
  "arrivalTime" : {
    "time" : 42432
  },
  "unloadTime" : {
    "time" : 47
  },
  "typeCargo" : "CONTAINER"
}, {
  "shipName" : "yKgKSLbbhRbGSGG",
  "tonnage" : 1095,
  "arrivalTime" : {
    "time" : 42507
  },
  "unloadTime" : {
    "time" : 55
  },
  "typeCargo" : "CONTAINER"
}, {
  "shipName" : "QRRXcPZRdUnjjWZ",
  "tonnage" : 914,
  "arrivalTime" : {
    "time" : 42519
  },
  "unloadTime" : {
    "time" : 46
  },
  "typeCargo" : "BULK"
}, {
  "shipName" : "NSZYTOYYCCbSaPT",
  "tonnage" : 977,
  "arrivalTime" : {
    "time" : 42761
  },
  "unloadTime" : {
    "time" : 49
  },
  "typeCargo" : "BULK"
}, {
  "shipName" : "TFMWWeLKSBp^PgF",
  "tonnage" : 943,
  "arrivalTime" : {
    "time" : 42785
  },
  "unloadTime" : {
    "time" : 48
  },
  "typeCargo" : "LIQUID"
}, {
  "shipName" : "VEQQMCYTHf\\Je]W",
  "tonnage" : 1183,
  "arrivalTime" : {
    "time" : 42978
  },
  "unloadTime" : {
    "time" : 60
  },
  "typeCargo" : "LIQUID"
}, {
  "shipName" : "K_VJiVXUMTO[dKb",
  "tonnage" : 977,
  "arrivalTime" : {
    "time" : 43024
  },
  "unloadTime" : {
    "time" : 49
  },
  "typeCargo" : "BULK"
}, {
  "shipName" : "\\YZFGp_nNeo^`GC",
  "tonnage" : 1070,
  "arrivalTime" : {
    "time" : 43055
  },
  "unloadTime" : {
    "time" : 54
  },
  "typeCargo" : "BULK"
}, {
  "shipName" : "_ZrnSbXMj[hTHmF",
  "tonnage" : 984,
  "arrivalTime" : {
    "time" : 43136
  },
  "unloadTime" : {
    "time" : 50
  },
  "typeCargo" : "BULK"
}, {
  "shipName" : "VQQVCrWUYfV\\P]A",
  "tonnage" : 922,
  "arrivalTime" : {
    "time" : 43174
  },
  "unloadTime" : {
    "time" : 47
  },
  "typeCargo" : "LIQUID"
}, {
  "shipName" : "I_A_D_KJ^SNjwqY",
  "tonnage" : 1193,
  "arrivalTime" : {
    "time" : 43223
  },
  "unloadTime" : {
    "time" : 60
  },
  "typeCargo" : "LIQUID"
}, {
  "shipName" : "DsO]sMTIROQMugS",
  "tonnage" : 1167,
  "arrivalTime" : {
    "time" : 43249
  },
  "unloadTime" : {
    "time" : 59
  },
  "typeCargo" : "CONTAINER"
}, {
  "shipName" : "RAIEfMaIv_XaTVX",
  "tonnage" : 1103,
  "arrivalTime" : {
    "time" : 43370
  },
  "unloadTime" : {
    "time" : 56
  },
  "typeCargo" : "BULK"
}, {
  "shipName" : "McCDJqZnVKnWYWa",
  "tonnage" : 973,
  "arrivalTime" : {
    "time" : 43547
  },
  "unloadTime" : {
    "time" : 49
  },
  "typeCargo" : "LIQUID"
}, {
  "shipName" : "[QPYSEROQObMBEW",
  "tonnage" : 1023,
  "arrivalTime" : {
    "time" : 43608
  },
  "unloadTime" : {
    "time" : 52
  },
  "typeCargo" : "LIQUID"
}, {
  "shipName" : "GFGwIUDBE^XEVfE",
  "tonnage" : 1142,
  "arrivalTime" : {
    "time" : 43680
  },
  "unloadTime" : {
    "time" : 58
  },
  "typeCargo" : "BULK"
}, {
  "shipName" : "uMXaWIJ^DhbZSX\\",
  "tonnage" : 1011,
  "arrivalTime" : {
    "time" : 43896
  },
  "unloadTime" : {
    "time" : 51
  },
  "typeCargo" : "LIQUID"
}, {
  "shipName" : "Kg_RgHMPRbacRaS",
  "tonnage" : 902,
  "arrivalTime" : {
    "time" : 44228
  },
  "unloadTime" : {
    "time" : 46
  },
  "typeCargo" : "BULK"
}, {
  "shipName" : "SccDYMWuRZX_VUX",
  "tonnage" : 1085,
  "arrivalTime" : {
    "time" : 44273
  },
  "unloadTime" : {
    "time" : 55
  },
  "typeCargo" : "CONTAINER"
}, {
  "shipName" : "SEp^MCebagVaFH`",
  "tonnage" : 1021,
  "arrivalTime" : {
    "time" : 44378
  },
  "unloadTime" : {
    "time" : 52
  },
  "typeCargo" : "CONTAINER"
}, {
  "shipName" : "MO[QbjK`QYvYLup",
  "tonnage" : 1090,
  "arrivalTime" : {
    "time" : 44399
  },
  "unloadTime" : {
    "time" : 55
  },
  "typeCargo" : "LIQUID"
}, {
  "shipName" : "ZLOWMBhTLPHLTYF",
  "tonnage" : 1046,
  "arrivalTime" : {
    "time" : 44452
  },
  "unloadTime" : {
    "time" : 53
  },
  "typeCargo" : "CONTAINER"
}, {
  "shipName" : "QKT[ID`QKETUGxC",
  "tonnage" : 1077,
  "arrivalTime" : {
    "time" : 44538
  },
  "unloadTime" : {
    "time" : 54
  },
  "typeCargo" : "BULK"
}, {
  "shipName" : "FOP`FVuRhLTgLR\\",
  "tonnage" : 1200,
  "arrivalTime" : {
    "time" : 44557
  },
  "unloadTime" : {
    "time" : 60
  },
  "typeCargo" : "BULK"
}, {
  "shipName" : "aBZNlnKjSSY[RTG",
  "tonnage" : 1063,
  "arrivalTime" : {
    "time" : 44624
  },
  "unloadTime" : {
    "time" : 54
  },
  "typeCargo" : "BULK"
}, {
  "shipName" : "sf[EQfflUYMOMJM",
  "tonnage" : 1190,
  "arrivalTime" : {
    "time" : 44794
  },
  "unloadTime" : {
    "time" : 60
  },
  "typeCargo" : "CONTAINER"
}, {
  "shipName" : "UXWReHWBdf^F]`K",
  "tonnage" : 1102,
  "arrivalTime" : {
    "time" : 44807
  },
  "unloadTime" : {
    "time" : 56
  },
  "typeCargo" : "LIQUID"
}, {
  "shipName" : "^QKADMf^YDXCM`h",
  "tonnage" : 1157,
  "arrivalTime" : {
    "time" : 44847
  },
  "unloadTime" : {
    "time" : 58
  },
  "typeCargo" : "CONTAINER"
}, {
  "shipName" : "_BunVKCjfAWPk[o",
  "tonnage" : 981,
  "arrivalTime" : {
    "time" : 44879
  },
  "unloadTime" : {
    "time" : 50
  },
  "typeCargo" : "CONTAINER"
}, {
  "shipName" : "qib]kYXHcFckO\\H",
  "tonnage" : 937,
  "arrivalTime" : {
    "time" : 44947
  },
  "unloadTime" : {
    "time" : 47
  },
  "typeCargo" : "CONTAINER"
}, {
  "shipName" : "`qNK_hMaAeUWT^b",
  "tonnage" : 1116,
  "arrivalTime" : {
    "time" : 45119
  },
  "unloadTime" : {
    "time" : 56
  },
  "typeCargo" : "LIQUID"
}, {
  "shipName" : "HCbVXARVfLJDWTo",
  "tonnage" : 1102,
  "arrivalTime" : {
    "time" : 45129
  },
  "unloadTime" : {
    "time" : 56
  },
  "typeCargo" : "LIQUID"
}, {
  "shipName" : "ATZZVQKINgFSITV",
  "tonnage" : 1157,
  "arrivalTime" : {
    "time" : 45186
  },
  "unloadTime" : {
    "time" : 58
  },
  "typeCargo" : "CONTAINER"
}, {
  "shipName" : "]UTpoLiTLVmdTYH",
  "tonnage" : 1097,
  "arrivalTime" : {
    "time" : 45277
  },
  "unloadTime" : {
    "time" : 55
  },
  "typeCargo" : "BULK"
}, {
  "shipName" : "qZXOXb`EKZELJVW",
  "tonnage" : 1174,
  "arrivalTime" : {
    "time" : 45307
  },
  "unloadTime" : {
    "time" : 59
  },
  "typeCargo" : "BULK"
}, {
  "shipName" : "EaY`TWeJBIXPCaH",
  "tonnage" : 1022,
  "arrivalTime" : {
    "time" : 45621
  },
  "unloadTime" : {
    "time" : 52
  },
  "typeCargo" : "CONTAINER"
}, {
  "shipName" : "cEiQTSihKWc[sOv",
  "tonnage" : 1185,
  "arrivalTime" : {
    "time" : 45871
  },
  "unloadTime" : {
    "time" : 60
  },
  "typeCargo" : "CONTAINER"
}, {
  "shipName" : "UbddKOLYcVcYCOM",
  "tonnage" : 1071,
  "arrivalTime" : {
    "time" : 46006
  },
  "unloadTime" : {
    "time" : 54
  },
  "typeCargo" : "BULK"
}, {
  "shipName" : "MbVMfdQYQMBncgT",
  "tonnage" : 929,
  "arrivalTime" : {
    "time" : 46119
  },
  "unloadTime" : {
    "time" : 47
  },
  "typeCargo" : "CONTAINER"
}, {
  "shipName" : "ZgVWOI\\Q`AXEWLL",
  "tonnage" : 961,
  "arrivalTime" : {
    "time" : 46375
  },
  "unloadTime" : {
    "time" : 49
  },
  "typeCargo" : "CONTAINER"
}, {
  "shipName" : "[C_UoVj_RVNGUKO",
  "tonnage" : 909,
  "arrivalTime" : {
    "time" : 46647
  },
  "unloadTime" : {
    "time" : 46
  },
  "typeCargo" : "LIQUID"
}, {
  "shipName" : "UghBMdWYZrFOdeH",
  "tonnage" : 1148,
  "arrivalTime" : {
    "time" : 46780
  },
  "unloadTime" : {
    "time" : 58
  },
  "typeCargo" : "BULK"
}, {
  "shipName" : "eGZATqKiJFmTIee",
  "tonnage" : 1063,
  "arrivalTime" : {
    "time" : 47198
  },
  "unloadTime" : {
    "time" : 54
  },
  "typeCargo" : "BULK"
}, {
  "shipName" : "ZMP_ccEMFNooOlU",
  "tonnage" : 943,
  "arrivalTime" : {
    "time" : 47291
  },
  "unloadTime" : {
    "time" : 48
  },
  "typeCargo" : "CONTAINER"
}, {
  "shipName" : "QKOcGnPNPNKPPBS",
  "tonnage" : 981,
  "arrivalTime" : {
    "time" : 47593
  },
  "unloadTime" : {
    "time" : 50
  },
  "typeCargo" : "LIQUID"
}, {
  "shipName" : "XLPSSQCXVFCiW^g",
  "tonnage" : 1037,
  "arrivalTime" : {
    "time" : 47643
  },
  "unloadTime" : {
    "time" : 52
  },
  "typeCargo" : "CONTAINER"
}, {
  "shipName" : "UcYpTjbshZbMHF]",
  "tonnage" : 1118,
  "arrivalTime" : {
    "time" : 47926
  },
  "unloadTime" : {
    "time" : 56
  },
  "typeCargo" : "CONTAINER"
}, {
  "shipName" : "A`tPUQPCkG]ZqqH",
  "tonnage" : 1073,
  "arrivalTime" : {
    "time" : 48106
  },
  "unloadTime" : {
    "time" : 54
  },
  "typeCargo" : "BULK"
}, {
  "shipName" : "gRhU`TP[fbMIXsP",
  "tonnage" : 1045,
  "arrivalTime" : {
    "time" : 48142
  },
  "unloadTime" : {
    "time" : 53
  },
  "typeCargo" : "CONTAINER"
}, {
  "shipName" : "BLYGJTV\\\\vWihOR",
  "tonnage" : 1161,
  "arrivalTime" : {
    "time" : 48313
  },
  "unloadTime" : {
    "time" : 59
  },
  "typeCargo" : "BULK"
}, {
  "shipName" : "UgrUNSCWXT[bxAq",
  "tonnage" : 1188,
  "arrivalTime" : {
    "time" : 48409
  },
  "unloadTime" : {
    "time" : 60
  },
  "typeCargo" : "BULK"
}, {
  "shipName" : "VfxPXYMaWcTTkAe",
  "tonnage" : 1066,
  "arrivalTime" : {
    "time" : 48414
  },
  "unloadTime" : {
    "time" : 54
  },
  "typeCargo" : "BULK"
}, {
  "shipName" : "QjMhBXYee_WLJBT",
  "tonnage" : 1082,
  "arrivalTime" : {
    "time" : 48720
  },
  "unloadTime" : {
    "time" : 55
  },
  "typeCargo" : "CONTAINER"
}, {
  "shipName" : "KMFXTSJabHEH\\Zb",
  "tonnage" : 960,
  "arrivalTime" : {
    "time" : 49162
  },
  "unloadTime" : {
    "time" : 48
  },
  "typeCargo" : "BULK"
}, {
  "shipName" : "nQq\\HClX`QVfEL[",
  "tonnage" : 1119,
  "arrivalTime" : {
    "time" : 49277
  },
  "unloadTime" : {
    "time" : 56
  },
  "typeCargo" : "BULK"
}, {
  "shipName" : "EUcbbRCAvhVGPL_",
  "tonnage" : 962,
  "arrivalTime" : {
    "time" : 49392
  },
  "unloadTime" : {
    "time" : 49
  },
  "typeCargo" : "CONTAINER"
}, {
  "shipName" : "iHS`OTZIFT\\`LF]",
  "tonnage" : 1149,
  "arrivalTime" : {
    "time" : 50296
  },
  "unloadTime" : {
    "time" : 58
  },
  "typeCargo" : "BULK"
}, {
  "shipName" : "cA`cFZQOWf\\XLSW",
  "tonnage" : 1077,
  "arrivalTime" : {
    "time" : 50308
  },
  "unloadTime" : {
    "time" : 54
  },
  "typeCargo" : "BULK"
}, {
  "shipName" : "PkjDq[C`LBOSPHC",
  "tonnage" : 1188,
  "arrivalTime" : {
    "time" : 51236
  },
  "unloadTime" : {
    "time" : 60
  },
  "typeCargo" : "LIQUID"
}, {
  "shipName" : "V\\NI^]pVefpHPDH",
  "tonnage" : 986,
  "arrivalTime" : {
    "time" : 51519
  },
  "unloadTime" : {
    "time" : 50
  },
  "typeCargo" : "BULK"
}, {
  "shipName" : "QZCPSgmIVBRGWRb",
  "tonnage" : 907,
  "arrivalTime" : {
    "time" : 51937
  },
  "unloadTime" : {
    "time" : 46
  },
  "typeCargo" : "CONTAINER"
} ]